{
	"clusters": [
		{
			"uid": "vhcxoqcufbksbxvsjpmbhyfacuwvhckfeylh",
			"name": "SA20153983",
			"loci": [
				{
					"uid": "syzazxvdjgbnnqrsoxdlbmvhdlvwjbwhohpb",
					"name": "SA20153983",
					"start": 138580,
					"end": 164530,
					"genes": [
						{
							"uid": "syzazxvdjgbnnqrsoxdlbmvhdlvwjbwhohpb-0",
							"name": "ftsA_2",
							"start": 138580,
							"end": 139843,
							"strand": -1
						},
						{
							"uid": "syzazxvdjgbnnqrsoxdlbmvhdlvwjbwhohpb-1",
							"name": "ftsQ",
							"start": 139839,
							"end": 140670,
							"strand": -1
						},
						{
							"uid": "syzazxvdjgbnnqrsoxdlbmvhdlvwjbwhohpb-2",
							"name": "ddlB",
							"start": 140671,
							"end": 141592,
							"strand": -1
						},
						{
							"uid": "syzazxvdjgbnnqrsoxdlbmvhdlvwjbwhohpb-3",
							"name": "murC",
							"start": 141584,
							"end": 143060,
							"strand": -1
						},
						{
							"uid": "syzazxvdjgbnnqrsoxdlbmvhdlvwjbwhohpb-4",
							"name": "murG",
							"start": 143178,
							"end": 144246,
							"strand": -1
						},
						{
							"uid": "syzazxvdjgbnnqrsoxdlbmvhdlvwjbwhohpb-5",
							"name": "ftsW",
							"start": 144242,
							"end": 145487,
							"strand": -1
						},
						{
							"uid": "syzazxvdjgbnnqrsoxdlbmvhdlvwjbwhohpb-6",
							"name": "murD",
							"start": 145486,
							"end": 146803,
							"strand": -1
						},
						{
							"uid": "syzazxvdjgbnnqrsoxdlbmvhdlvwjbwhohpb-7",
							"name": "mraY",
							"start": 146805,
							"end": 147888,
							"strand": -1
						},
						{
							"uid": "syzazxvdjgbnnqrsoxdlbmvhdlvwjbwhohpb-8",
							"name": "murF",
							"start": 147881,
							"end": 149240,
							"strand": -1
						},
						{
							"uid": "syzazxvdjgbnnqrsoxdlbmvhdlvwjbwhohpb-9",
							"name": "murE",
							"start": 149236,
							"end": 150724,
							"strand": -1
						},
						{
							"uid": "syzazxvdjgbnnqrsoxdlbmvhdlvwjbwhohpb-10",
							"name": "ftsI_2",
							"start": 150710,
							"end": 152477,
							"strand": -1
						},
						{
							"uid": "syzazxvdjgbnnqrsoxdlbmvhdlvwjbwhohpb-11",
							"name": "ftsL",
							"start": 152492,
							"end": 152858,
							"strand": -1
						},
						{
							"uid": "syzazxvdjgbnnqrsoxdlbmvhdlvwjbwhohpb-12",
							"name": "rsmH",
							"start": 152854,
							"end": 153796,
							"strand": -1
						},
						{
							"uid": "syzazxvdjgbnnqrsoxdlbmvhdlvwjbwhohpb-13",
							"name": "mraZ",
							"start": 153797,
							"end": 154256,
							"strand": -1
						},
						{
							"uid": "syzazxvdjgbnnqrsoxdlbmvhdlvwjbwhohpb-14",
							"name": "cra",
							"start": 154861,
							"end": 155866,
							"strand": -1
						},
						{
							"uid": "syzazxvdjgbnnqrsoxdlbmvhdlvwjbwhohpb-15",
							"name": "ilvH",
							"start": 156149,
							"end": 156644,
							"strand": -1
						},
						{
							"uid": "syzazxvdjgbnnqrsoxdlbmvhdlvwjbwhohpb-16",
							"name": "ilvI",
							"start": 156643,
							"end": 158368,
							"strand": -1
						},
						{
							"uid": "syzazxvdjgbnnqrsoxdlbmvhdlvwjbwhohpb-17",
							"name": "leuO_1",
							"start": 158689,
							"end": 159634,
							"strand": -1
						},
						{
							"uid": "syzazxvdjgbnnqrsoxdlbmvhdlvwjbwhohpb-18",
							"name": "leuA",
							"start": 160464,
							"end": 162036,
							"strand": 1
						},
						{
							"uid": "syzazxvdjgbnnqrsoxdlbmvhdlvwjbwhohpb-19",
							"name": "leuB",
							"start": 162035,
							"end": 163127,
							"strand": 1
						},
						{
							"uid": "syzazxvdjgbnnqrsoxdlbmvhdlvwjbwhohpb-20",
							"name": "leuC1",
							"start": 163129,
							"end": 164530,
							"strand": 1
						}
					]
				}
			]
		},
		{
			"uid": "oqofwccqjkwigvkyjeosttoivgqfbwoftlxs",
			"name": "SA20160197",
			"loci": [
				{
					"uid": "shncgijylmrzyxngguztabvawkcocibthsit",
					"name": "SA20160197",
					"start": 62993,
					"end": 88943,
					"genes": [
						{
							"uid": "shncgijylmrzyxngguztabvawkcocibthsit-0",
							"name": "leuC1",
							"start": 62993,
							"end": 64394,
							"strand": -1
						},
						{
							"uid": "shncgijylmrzyxngguztabvawkcocibthsit-1",
							"name": "leuB",
							"start": 64396,
							"end": 65488,
							"strand": -1
						},
						{
							"uid": "shncgijylmrzyxngguztabvawkcocibthsit-2",
							"name": "leuA",
							"start": 65487,
							"end": 67059,
							"strand": -1
						},
						{
							"uid": "shncgijylmrzyxngguztabvawkcocibthsit-3",
							"name": "leuO",
							"start": 67889,
							"end": 68834,
							"strand": 1
						},
						{
							"uid": "shncgijylmrzyxngguztabvawkcocibthsit-4",
							"name": "ilvI",
							"start": 69155,
							"end": 70880,
							"strand": 1
						},
						{
							"uid": "shncgijylmrzyxngguztabvawkcocibthsit-5",
							"name": "ilvH",
							"start": 70879,
							"end": 71374,
							"strand": 1
						},
						{
							"uid": "shncgijylmrzyxngguztabvawkcocibthsit-6",
							"name": "cra",
							"start": 71657,
							"end": 72662,
							"strand": 1
						},
						{
							"uid": "shncgijylmrzyxngguztabvawkcocibthsit-7",
							"name": "mraZ",
							"start": 73267,
							"end": 73726,
							"strand": 1
						},
						{
							"uid": "shncgijylmrzyxngguztabvawkcocibthsit-8",
							"name": "rsmH",
							"start": 73727,
							"end": 74669,
							"strand": 1
						},
						{
							"uid": "shncgijylmrzyxngguztabvawkcocibthsit-9",
							"name": "ftsL",
							"start": 74665,
							"end": 75031,
							"strand": 1
						},
						{
							"uid": "shncgijylmrzyxngguztabvawkcocibthsit-10",
							"name": "ftsI_2",
							"start": 75046,
							"end": 76813,
							"strand": 1
						},
						{
							"uid": "shncgijylmrzyxngguztabvawkcocibthsit-11",
							"name": "murE",
							"start": 76799,
							"end": 78287,
							"strand": 1
						},
						{
							"uid": "shncgijylmrzyxngguztabvawkcocibthsit-12",
							"name": "murF",
							"start": 78283,
							"end": 79642,
							"strand": 1
						},
						{
							"uid": "shncgijylmrzyxngguztabvawkcocibthsit-13",
							"name": "mraY",
							"start": 79635,
							"end": 80718,
							"strand": 1
						},
						{
							"uid": "shncgijylmrzyxngguztabvawkcocibthsit-14",
							"name": "murD",
							"start": 80720,
							"end": 82037,
							"strand": 1
						},
						{
							"uid": "shncgijylmrzyxngguztabvawkcocibthsit-15",
							"name": "ftsW",
							"start": 82036,
							"end": 83281,
							"strand": 1
						},
						{
							"uid": "shncgijylmrzyxngguztabvawkcocibthsit-16",
							"name": "murG",
							"start": 83277,
							"end": 84345,
							"strand": 1
						},
						{
							"uid": "shncgijylmrzyxngguztabvawkcocibthsit-17",
							"name": "murC",
							"start": 84463,
							"end": 85939,
							"strand": 1
						},
						{
							"uid": "shncgijylmrzyxngguztabvawkcocibthsit-18",
							"name": "ddlB",
							"start": 85931,
							"end": 86852,
							"strand": 1
						},
						{
							"uid": "shncgijylmrzyxngguztabvawkcocibthsit-19",
							"name": "ftsQ",
							"start": 86853,
							"end": 87684,
							"strand": 1
						},
						{
							"uid": "shncgijylmrzyxngguztabvawkcocibthsit-20",
							"name": "ftsA_1",
							"start": 87680,
							"end": 88943,
							"strand": 1
						}
					]
				}
			]
		},
		{
			"uid": "roiyrnzsyxigjqlxkherbahxlyharljdaxvl",
			"name": "SA20160228",
			"loci": [
				{
					"uid": "kokqyqyrupwkmphgvafeziybldkujwrmqstx",
					"name": "SA20160228",
					"start": 63342,
					"end": 89292,
					"genes": [
						{
							"uid": "kokqyqyrupwkmphgvafeziybldkujwrmqstx-0",
							"name": "leuC1",
							"start": 63342,
							"end": 64743,
							"strand": -1
						},
						{
							"uid": "kokqyqyrupwkmphgvafeziybldkujwrmqstx-1",
							"name": "leuB",
							"start": 64745,
							"end": 65837,
							"strand": -1
						},
						{
							"uid": "kokqyqyrupwkmphgvafeziybldkujwrmqstx-2",
							"name": "leuA",
							"start": 65836,
							"end": 67408,
							"strand": -1
						},
						{
							"uid": "kokqyqyrupwkmphgvafeziybldkujwrmqstx-3",
							"name": "leuO",
							"start": 68238,
							"end": 69183,
							"strand": 1
						},
						{
							"uid": "kokqyqyrupwkmphgvafeziybldkujwrmqstx-4",
							"name": "ilvI",
							"start": 69504,
							"end": 71229,
							"strand": 1
						},
						{
							"uid": "kokqyqyrupwkmphgvafeziybldkujwrmqstx-5",
							"name": "ilvH",
							"start": 71228,
							"end": 71723,
							"strand": 1
						},
						{
							"uid": "kokqyqyrupwkmphgvafeziybldkujwrmqstx-6",
							"name": "cra",
							"start": 72006,
							"end": 73011,
							"strand": 1
						},
						{
							"uid": "kokqyqyrupwkmphgvafeziybldkujwrmqstx-7",
							"name": "mraZ",
							"start": 73616,
							"end": 74075,
							"strand": 1
						},
						{
							"uid": "kokqyqyrupwkmphgvafeziybldkujwrmqstx-8",
							"name": "rsmH",
							"start": 74076,
							"end": 75018,
							"strand": 1
						},
						{
							"uid": "kokqyqyrupwkmphgvafeziybldkujwrmqstx-9",
							"name": "ftsL",
							"start": 75014,
							"end": 75380,
							"strand": 1
						},
						{
							"uid": "kokqyqyrupwkmphgvafeziybldkujwrmqstx-10",
							"name": "ftsI_2",
							"start": 75395,
							"end": 77162,
							"strand": 1
						},
						{
							"uid": "kokqyqyrupwkmphgvafeziybldkujwrmqstx-11",
							"name": "murE",
							"start": 77148,
							"end": 78636,
							"strand": 1
						},
						{
							"uid": "kokqyqyrupwkmphgvafeziybldkujwrmqstx-12",
							"name": "murF",
							"start": 78632,
							"end": 79991,
							"strand": 1
						},
						{
							"uid": "kokqyqyrupwkmphgvafeziybldkujwrmqstx-13",
							"name": "mraY",
							"start": 79984,
							"end": 81067,
							"strand": 1
						},
						{
							"uid": "kokqyqyrupwkmphgvafeziybldkujwrmqstx-14",
							"name": "murD",
							"start": 81069,
							"end": 82386,
							"strand": 1
						},
						{
							"uid": "kokqyqyrupwkmphgvafeziybldkujwrmqstx-15",
							"name": "ftsW",
							"start": 82385,
							"end": 83630,
							"strand": 1
						},
						{
							"uid": "kokqyqyrupwkmphgvafeziybldkujwrmqstx-16",
							"name": "murG",
							"start": 83626,
							"end": 84694,
							"strand": 1
						},
						{
							"uid": "kokqyqyrupwkmphgvafeziybldkujwrmqstx-17",
							"name": "murC",
							"start": 84812,
							"end": 86288,
							"strand": 1
						},
						{
							"uid": "kokqyqyrupwkmphgvafeziybldkujwrmqstx-18",
							"name": "ddlB",
							"start": 86280,
							"end": 87201,
							"strand": 1
						},
						{
							"uid": "kokqyqyrupwkmphgvafeziybldkujwrmqstx-19",
							"name": "ftsQ",
							"start": 87202,
							"end": 88033,
							"strand": 1
						},
						{
							"uid": "kokqyqyrupwkmphgvafeziybldkujwrmqstx-20",
							"name": "ftsA_1",
							"start": 88029,
							"end": 89292,
							"strand": 1
						}
					]
				}
			]
		},
		{
			"uid": "jclgzexlxppkyuuokcjefwuantevbkmvulyw",
			"name": "SA20160326",
			"loci": [
				{
					"uid": "fibnrjmrupgbvqncwcspjxlfdqdbqwvuesum",
					"name": "SA20160326",
					"start": 63342,
					"end": 89292,
					"genes": [
						{
							"uid": "fibnrjmrupgbvqncwcspjxlfdqdbqwvuesum-0",
							"name": "leuC1",
							"start": 63342,
							"end": 64743,
							"strand": -1
						},
						{
							"uid": "fibnrjmrupgbvqncwcspjxlfdqdbqwvuesum-1",
							"name": "leuB",
							"start": 64745,
							"end": 65837,
							"strand": -1
						},
						{
							"uid": "fibnrjmrupgbvqncwcspjxlfdqdbqwvuesum-2",
							"name": "leuA",
							"start": 65836,
							"end": 67408,
							"strand": -1
						},
						{
							"uid": "fibnrjmrupgbvqncwcspjxlfdqdbqwvuesum-3",
							"name": "leuO",
							"start": 68238,
							"end": 69183,
							"strand": 1
						},
						{
							"uid": "fibnrjmrupgbvqncwcspjxlfdqdbqwvuesum-4",
							"name": "ilvI",
							"start": 69504,
							"end": 71229,
							"strand": 1
						},
						{
							"uid": "fibnrjmrupgbvqncwcspjxlfdqdbqwvuesum-5",
							"name": "ilvH",
							"start": 71228,
							"end": 71723,
							"strand": 1
						},
						{
							"uid": "fibnrjmrupgbvqncwcspjxlfdqdbqwvuesum-6",
							"name": "cra",
							"start": 72006,
							"end": 73011,
							"strand": 1
						},
						{
							"uid": "fibnrjmrupgbvqncwcspjxlfdqdbqwvuesum-7",
							"name": "mraZ",
							"start": 73616,
							"end": 74075,
							"strand": 1
						},
						{
							"uid": "fibnrjmrupgbvqncwcspjxlfdqdbqwvuesum-8",
							"name": "rsmH",
							"start": 74076,
							"end": 75018,
							"strand": 1
						},
						{
							"uid": "fibnrjmrupgbvqncwcspjxlfdqdbqwvuesum-9",
							"name": "ftsL",
							"start": 75014,
							"end": 75380,
							"strand": 1
						},
						{
							"uid": "fibnrjmrupgbvqncwcspjxlfdqdbqwvuesum-10",
							"name": "ftsI_2",
							"start": 75395,
							"end": 77162,
							"strand": 1
						},
						{
							"uid": "fibnrjmrupgbvqncwcspjxlfdqdbqwvuesum-11",
							"name": "murE",
							"start": 77148,
							"end": 78636,
							"strand": 1
						},
						{
							"uid": "fibnrjmrupgbvqncwcspjxlfdqdbqwvuesum-12",
							"name": "murF",
							"start": 78632,
							"end": 79991,
							"strand": 1
						},
						{
							"uid": "fibnrjmrupgbvqncwcspjxlfdqdbqwvuesum-13",
							"name": "mraY",
							"start": 79984,
							"end": 81067,
							"strand": 1
						},
						{
							"uid": "fibnrjmrupgbvqncwcspjxlfdqdbqwvuesum-14",
							"name": "murD",
							"start": 81069,
							"end": 82386,
							"strand": 1
						},
						{
							"uid": "fibnrjmrupgbvqncwcspjxlfdqdbqwvuesum-15",
							"name": "ftsW",
							"start": 82385,
							"end": 83630,
							"strand": 1
						},
						{
							"uid": "fibnrjmrupgbvqncwcspjxlfdqdbqwvuesum-16",
							"name": "murG",
							"start": 83626,
							"end": 84694,
							"strand": 1
						},
						{
							"uid": "fibnrjmrupgbvqncwcspjxlfdqdbqwvuesum-17",
							"name": "murC",
							"start": 84812,
							"end": 86288,
							"strand": 1
						},
						{
							"uid": "fibnrjmrupgbvqncwcspjxlfdqdbqwvuesum-18",
							"name": "ddlB",
							"start": 86280,
							"end": 87201,
							"strand": 1
						},
						{
							"uid": "fibnrjmrupgbvqncwcspjxlfdqdbqwvuesum-19",
							"name": "ftsQ",
							"start": 87202,
							"end": 88033,
							"strand": 1
						},
						{
							"uid": "fibnrjmrupgbvqncwcspjxlfdqdbqwvuesum-20",
							"name": "ftsA_2",
							"start": 88029,
							"end": 89292,
							"strand": 1
						}
					]
				}
			]
		},
		{
			"uid": "ajjwiyqipazljiamsxvwpsucgtlgphlwzgwu",
			"name": "SA20160201",
			"loci": [
				{
					"uid": "tmbumlpqopzbkiqwcnzbysiajbveyatjqchf",
					"name": "SA20160201",
					"start": 146134,
					"end": 172084,
					"genes": [
						{
							"uid": "tmbumlpqopzbkiqwcnzbysiajbveyatjqchf-0",
							"name": "ftsA_1",
							"start": 146134,
							"end": 147397,
							"strand": -1
						},
						{
							"uid": "tmbumlpqopzbkiqwcnzbysiajbveyatjqchf-1",
							"name": "ftsQ",
							"start": 147393,
							"end": 148224,
							"strand": -1
						},
						{
							"uid": "tmbumlpqopzbkiqwcnzbysiajbveyatjqchf-2",
							"name": "ddlB",
							"start": 148225,
							"end": 149146,
							"strand": -1
						},
						{
							"uid": "tmbumlpqopzbkiqwcnzbysiajbveyatjqchf-3",
							"name": "murC",
							"start": 149138,
							"end": 150614,
							"strand": -1
						},
						{
							"uid": "tmbumlpqopzbkiqwcnzbysiajbveyatjqchf-4",
							"name": "murG",
							"start": 150732,
							"end": 151800,
							"strand": -1
						},
						{
							"uid": "tmbumlpqopzbkiqwcnzbysiajbveyatjqchf-5",
							"name": "ftsW",
							"start": 151796,
							"end": 153041,
							"strand": -1
						},
						{
							"uid": "tmbumlpqopzbkiqwcnzbysiajbveyatjqchf-6",
							"name": "murD",
							"start": 153040,
							"end": 154357,
							"strand": -1
						},
						{
							"uid": "tmbumlpqopzbkiqwcnzbysiajbveyatjqchf-7",
							"name": "mraY",
							"start": 154359,
							"end": 155442,
							"strand": -1
						},
						{
							"uid": "tmbumlpqopzbkiqwcnzbysiajbveyatjqchf-8",
							"name": "murF",
							"start": 155435,
							"end": 156794,
							"strand": -1
						},
						{
							"uid": "tmbumlpqopzbkiqwcnzbysiajbveyatjqchf-9",
							"name": "murE",
							"start": 156790,
							"end": 158278,
							"strand": -1
						},
						{
							"uid": "tmbumlpqopzbkiqwcnzbysiajbveyatjqchf-10",
							"name": "ftsI_1",
							"start": 158264,
							"end": 160031,
							"strand": -1
						},
						{
							"uid": "tmbumlpqopzbkiqwcnzbysiajbveyatjqchf-11",
							"name": "ftsL",
							"start": 160046,
							"end": 160412,
							"strand": -1
						},
						{
							"uid": "tmbumlpqopzbkiqwcnzbysiajbveyatjqchf-12",
							"name": "rsmH",
							"start": 160408,
							"end": 161350,
							"strand": -1
						},
						{
							"uid": "tmbumlpqopzbkiqwcnzbysiajbveyatjqchf-13",
							"name": "mraZ",
							"start": 161351,
							"end": 161810,
							"strand": -1
						},
						{
							"uid": "tmbumlpqopzbkiqwcnzbysiajbveyatjqchf-14",
							"name": "cra",
							"start": 162415,
							"end": 163420,
							"strand": -1
						},
						{
							"uid": "tmbumlpqopzbkiqwcnzbysiajbveyatjqchf-15",
							"name": "ilvH",
							"start": 163703,
							"end": 164198,
							"strand": -1
						},
						{
							"uid": "tmbumlpqopzbkiqwcnzbysiajbveyatjqchf-16",
							"name": "ilvI",
							"start": 164197,
							"end": 165922,
							"strand": -1
						},
						{
							"uid": "tmbumlpqopzbkiqwcnzbysiajbveyatjqchf-17",
							"name": "leuO",
							"start": 166243,
							"end": 167188,
							"strand": -1
						},
						{
							"uid": "tmbumlpqopzbkiqwcnzbysiajbveyatjqchf-18",
							"name": "leuA",
							"start": 168018,
							"end": 169590,
							"strand": 1
						},
						{
							"uid": "tmbumlpqopzbkiqwcnzbysiajbveyatjqchf-19",
							"name": "leuB",
							"start": 169589,
							"end": 170681,
							"strand": 1
						},
						{
							"uid": "tmbumlpqopzbkiqwcnzbysiajbveyatjqchf-20",
							"name": "leuC1",
							"start": 170683,
							"end": 172084,
							"strand": 1
						}
					]
				}
			]
		},
		{
			"uid": "pqtvfaskztmaaeybmjyjetktfdrjijqwhsga",
			"name": "SA20160170",
			"loci": [
				{
					"uid": "lkmhkflfaiuhikosucymdifroqxdkhoupifr",
					"name": "SA20160170",
					"start": 63343,
					"end": 89293,
					"genes": [
						{
							"uid": "lkmhkflfaiuhikosucymdifroqxdkhoupifr-0",
							"name": "leuC1",
							"start": 63343,
							"end": 64744,
							"strand": -1
						},
						{
							"uid": "lkmhkflfaiuhikosucymdifroqxdkhoupifr-1",
							"name": "leuB",
							"start": 64746,
							"end": 65838,
							"strand": -1
						},
						{
							"uid": "lkmhkflfaiuhikosucymdifroqxdkhoupifr-2",
							"name": "leuA",
							"start": 65837,
							"end": 67409,
							"strand": -1
						},
						{
							"uid": "lkmhkflfaiuhikosucymdifroqxdkhoupifr-3",
							"name": "leuO",
							"start": 68239,
							"end": 69184,
							"strand": 1
						},
						{
							"uid": "lkmhkflfaiuhikosucymdifroqxdkhoupifr-4",
							"name": "ilvI",
							"start": 69505,
							"end": 71230,
							"strand": 1
						},
						{
							"uid": "lkmhkflfaiuhikosucymdifroqxdkhoupifr-5",
							"name": "ilvH",
							"start": 71229,
							"end": 71724,
							"strand": 1
						},
						{
							"uid": "lkmhkflfaiuhikosucymdifroqxdkhoupifr-6",
							"name": "cra",
							"start": 72007,
							"end": 73012,
							"strand": 1
						},
						{
							"uid": "lkmhkflfaiuhikosucymdifroqxdkhoupifr-7",
							"name": "mraZ",
							"start": 73617,
							"end": 74076,
							"strand": 1
						},
						{
							"uid": "lkmhkflfaiuhikosucymdifroqxdkhoupifr-8",
							"name": "rsmH",
							"start": 74077,
							"end": 75019,
							"strand": 1
						},
						{
							"uid": "lkmhkflfaiuhikosucymdifroqxdkhoupifr-9",
							"name": "ftsL",
							"start": 75015,
							"end": 75381,
							"strand": 1
						},
						{
							"uid": "lkmhkflfaiuhikosucymdifroqxdkhoupifr-10",
							"name": "ftsI_2",
							"start": 75396,
							"end": 77163,
							"strand": 1
						},
						{
							"uid": "lkmhkflfaiuhikosucymdifroqxdkhoupifr-11",
							"name": "murE",
							"start": 77149,
							"end": 78637,
							"strand": 1
						},
						{
							"uid": "lkmhkflfaiuhikosucymdifroqxdkhoupifr-12",
							"name": "murF",
							"start": 78633,
							"end": 79992,
							"strand": 1
						},
						{
							"uid": "lkmhkflfaiuhikosucymdifroqxdkhoupifr-13",
							"name": "mraY",
							"start": 79985,
							"end": 81068,
							"strand": 1
						},
						{
							"uid": "lkmhkflfaiuhikosucymdifroqxdkhoupifr-14",
							"name": "murD",
							"start": 81070,
							"end": 82387,
							"strand": 1
						},
						{
							"uid": "lkmhkflfaiuhikosucymdifroqxdkhoupifr-15",
							"name": "ftsW",
							"start": 82386,
							"end": 83631,
							"strand": 1
						},
						{
							"uid": "lkmhkflfaiuhikosucymdifroqxdkhoupifr-16",
							"name": "murG",
							"start": 83627,
							"end": 84695,
							"strand": 1
						},
						{
							"uid": "lkmhkflfaiuhikosucymdifroqxdkhoupifr-17",
							"name": "murC",
							"start": 84813,
							"end": 86289,
							"strand": 1
						},
						{
							"uid": "lkmhkflfaiuhikosucymdifroqxdkhoupifr-18",
							"name": "ddlB",
							"start": 86281,
							"end": 87202,
							"strand": 1
						},
						{
							"uid": "lkmhkflfaiuhikosucymdifroqxdkhoupifr-19",
							"name": "ftsQ",
							"start": 87203,
							"end": 88034,
							"strand": 1
						},
						{
							"uid": "lkmhkflfaiuhikosucymdifroqxdkhoupifr-20",
							"name": "ftsA_1",
							"start": 88030,
							"end": 89293,
							"strand": 1
						}
					]
				}
			]
		},
		{
			"uid": "ycxfcwpavnczbzasgocvbkbyojvwdwbcxssc",
			"name": "SA20160323",
			"loci": [
				{
					"uid": "srhwliukqgwasifxrnnjmlxxipiqietrykhi",
					"name": "SA20160323",
					"start": 147582,
					"end": 173531,
					"genes": [
						{
							"uid": "srhwliukqgwasifxrnnjmlxxipiqietrykhi-0",
							"name": "ftsA_2",
							"start": 147582,
							"end": 148845,
							"strand": -1
						},
						{
							"uid": "srhwliukqgwasifxrnnjmlxxipiqietrykhi-1",
							"name": "ftsQ",
							"start": 148841,
							"end": 149672,
							"strand": -1
						},
						{
							"uid": "srhwliukqgwasifxrnnjmlxxipiqietrykhi-2",
							"name": "ddlB",
							"start": 149673,
							"end": 150594,
							"strand": -1
						},
						{
							"uid": "srhwliukqgwasifxrnnjmlxxipiqietrykhi-3",
							"name": "murC",
							"start": 150586,
							"end": 152062,
							"strand": -1
						},
						{
							"uid": "srhwliukqgwasifxrnnjmlxxipiqietrykhi-4",
							"name": "murG",
							"start": 152180,
							"end": 153248,
							"strand": -1
						},
						{
							"uid": "srhwliukqgwasifxrnnjmlxxipiqietrykhi-5",
							"name": "ftsW",
							"start": 153244,
							"end": 154489,
							"strand": -1
						},
						{
							"uid": "srhwliukqgwasifxrnnjmlxxipiqietrykhi-6",
							"name": "murD",
							"start": 154488,
							"end": 155805,
							"strand": -1
						},
						{
							"uid": "srhwliukqgwasifxrnnjmlxxipiqietrykhi-7",
							"name": "mraY",
							"start": 155807,
							"end": 156890,
							"strand": -1
						},
						{
							"uid": "srhwliukqgwasifxrnnjmlxxipiqietrykhi-8",
							"name": "murF",
							"start": 156883,
							"end": 158242,
							"strand": -1
						},
						{
							"uid": "srhwliukqgwasifxrnnjmlxxipiqietrykhi-9",
							"name": "murE",
							"start": 158238,
							"end": 159726,
							"strand": -1
						},
						{
							"uid": "srhwliukqgwasifxrnnjmlxxipiqietrykhi-10",
							"name": "ftsI_1",
							"start": 159712,
							"end": 161479,
							"strand": -1
						},
						{
							"uid": "srhwliukqgwasifxrnnjmlxxipiqietrykhi-11",
							"name": "ftsL",
							"start": 161494,
							"end": 161860,
							"strand": -1
						},
						{
							"uid": "srhwliukqgwasifxrnnjmlxxipiqietrykhi-12",
							"name": "rsmH",
							"start": 161856,
							"end": 162798,
							"strand": -1
						},
						{
							"uid": "srhwliukqgwasifxrnnjmlxxipiqietrykhi-13",
							"name": "mraZ",
							"start": 162799,
							"end": 163258,
							"strand": -1
						},
						{
							"uid": "srhwliukqgwasifxrnnjmlxxipiqietrykhi-14",
							"name": "cra",
							"start": 163863,
							"end": 164868,
							"strand": -1
						},
						{
							"uid": "srhwliukqgwasifxrnnjmlxxipiqietrykhi-15",
							"name": "ilvH",
							"start": 165150,
							"end": 165645,
							"strand": -1
						},
						{
							"uid": "srhwliukqgwasifxrnnjmlxxipiqietrykhi-16",
							"name": "ilvI",
							"start": 165644,
							"end": 167369,
							"strand": -1
						},
						{
							"uid": "srhwliukqgwasifxrnnjmlxxipiqietrykhi-17",
							"name": "leuO",
							"start": 167690,
							"end": 168635,
							"strand": -1
						},
						{
							"uid": "srhwliukqgwasifxrnnjmlxxipiqietrykhi-18",
							"name": "leuA",
							"start": 169465,
							"end": 171037,
							"strand": 1
						},
						{
							"uid": "srhwliukqgwasifxrnnjmlxxipiqietrykhi-19",
							"name": "leuB",
							"start": 171036,
							"end": 172128,
							"strand": 1
						},
						{
							"uid": "srhwliukqgwasifxrnnjmlxxipiqietrykhi-20",
							"name": "leuC1",
							"start": 172130,
							"end": 173531,
							"strand": 1
						}
					]
				}
			]
		},
		{
			"uid": "pooaswlwxxqwhqcmhlffxrsqibexhhrvcdtj",
			"name": "SA20160203",
			"loci": [
				{
					"uid": "lzezkmktpaooltqqxjjshhwuwzvqgatfnyhk",
					"name": "SA20160203",
					"start": 146132,
					"end": 172082,
					"genes": [
						{
							"uid": "lzezkmktpaooltqqxjjshhwuwzvqgatfnyhk-0",
							"name": "ftsA_2",
							"start": 146132,
							"end": 147395,
							"strand": -1
						},
						{
							"uid": "lzezkmktpaooltqqxjjshhwuwzvqgatfnyhk-1",
							"name": "ftsQ",
							"start": 147391,
							"end": 148222,
							"strand": -1
						},
						{
							"uid": "lzezkmktpaooltqqxjjshhwuwzvqgatfnyhk-2",
							"name": "ddlB",
							"start": 148223,
							"end": 149144,
							"strand": -1
						},
						{
							"uid": "lzezkmktpaooltqqxjjshhwuwzvqgatfnyhk-3",
							"name": "murC",
							"start": 149136,
							"end": 150612,
							"strand": -1
						},
						{
							"uid": "lzezkmktpaooltqqxjjshhwuwzvqgatfnyhk-4",
							"name": "murG",
							"start": 150730,
							"end": 151798,
							"strand": -1
						},
						{
							"uid": "lzezkmktpaooltqqxjjshhwuwzvqgatfnyhk-5",
							"name": "ftsW",
							"start": 151794,
							"end": 153039,
							"strand": -1
						},
						{
							"uid": "lzezkmktpaooltqqxjjshhwuwzvqgatfnyhk-6",
							"name": "murD",
							"start": 153038,
							"end": 154355,
							"strand": -1
						},
						{
							"uid": "lzezkmktpaooltqqxjjshhwuwzvqgatfnyhk-7",
							"name": "mraY",
							"start": 154357,
							"end": 155440,
							"strand": -1
						},
						{
							"uid": "lzezkmktpaooltqqxjjshhwuwzvqgatfnyhk-8",
							"name": "murF",
							"start": 155433,
							"end": 156792,
							"strand": -1
						},
						{
							"uid": "lzezkmktpaooltqqxjjshhwuwzvqgatfnyhk-9",
							"name": "murE",
							"start": 156788,
							"end": 158276,
							"strand": -1
						},
						{
							"uid": "lzezkmktpaooltqqxjjshhwuwzvqgatfnyhk-10",
							"name": "ftsI_2",
							"start": 158262,
							"end": 160029,
							"strand": -1
						},
						{
							"uid": "lzezkmktpaooltqqxjjshhwuwzvqgatfnyhk-11",
							"name": "ftsL",
							"start": 160044,
							"end": 160410,
							"strand": -1
						},
						{
							"uid": "lzezkmktpaooltqqxjjshhwuwzvqgatfnyhk-12",
							"name": "rsmH",
							"start": 160406,
							"end": 161348,
							"strand": -1
						},
						{
							"uid": "lzezkmktpaooltqqxjjshhwuwzvqgatfnyhk-13",
							"name": "mraZ",
							"start": 161349,
							"end": 161808,
							"strand": -1
						},
						{
							"uid": "lzezkmktpaooltqqxjjshhwuwzvqgatfnyhk-14",
							"name": "cra",
							"start": 162413,
							"end": 163418,
							"strand": -1
						},
						{
							"uid": "lzezkmktpaooltqqxjjshhwuwzvqgatfnyhk-15",
							"name": "ilvH",
							"start": 163701,
							"end": 164196,
							"strand": -1
						},
						{
							"uid": "lzezkmktpaooltqqxjjshhwuwzvqgatfnyhk-16",
							"name": "ilvI",
							"start": 164195,
							"end": 165920,
							"strand": -1
						},
						{
							"uid": "lzezkmktpaooltqqxjjshhwuwzvqgatfnyhk-17",
							"name": "leuO",
							"start": 166241,
							"end": 167186,
							"strand": -1
						},
						{
							"uid": "lzezkmktpaooltqqxjjshhwuwzvqgatfnyhk-18",
							"name": "leuA",
							"start": 168016,
							"end": 169588,
							"strand": 1
						},
						{
							"uid": "lzezkmktpaooltqqxjjshhwuwzvqgatfnyhk-19",
							"name": "leuB",
							"start": 169587,
							"end": 170679,
							"strand": 1
						},
						{
							"uid": "lzezkmktpaooltqqxjjshhwuwzvqgatfnyhk-20",
							"name": "leuC1",
							"start": 170681,
							"end": 172082,
							"strand": 1
						}
					]
				}
			]
		},
		{
			"uid": "pcmkaqhqupnctxqxdfgzpphwqkbchdxrbptj",
			"name": "SA20160209",
			"loci": [
				{
					"uid": "kmrjuxgfqadpgxwzajvjfhpjefrfhsrkdjps",
					"name": "SA20160209",
					"start": 146135,
					"end": 172085,
					"genes": [
						{
							"uid": "kmrjuxgfqadpgxwzajvjfhpjefrfhsrkdjps-0",
							"name": "ftsA_1",
							"start": 146135,
							"end": 147398,
							"strand": -1
						},
						{
							"uid": "kmrjuxgfqadpgxwzajvjfhpjefrfhsrkdjps-1",
							"name": "ftsQ",
							"start": 147394,
							"end": 148225,
							"strand": -1
						},
						{
							"uid": "kmrjuxgfqadpgxwzajvjfhpjefrfhsrkdjps-2",
							"name": "ddlB",
							"start": 148226,
							"end": 149147,
							"strand": -1
						},
						{
							"uid": "kmrjuxgfqadpgxwzajvjfhpjefrfhsrkdjps-3",
							"name": "murC",
							"start": 149139,
							"end": 150615,
							"strand": -1
						},
						{
							"uid": "kmrjuxgfqadpgxwzajvjfhpjefrfhsrkdjps-4",
							"name": "murG",
							"start": 150733,
							"end": 151801,
							"strand": -1
						},
						{
							"uid": "kmrjuxgfqadpgxwzajvjfhpjefrfhsrkdjps-5",
							"name": "ftsW",
							"start": 151797,
							"end": 153042,
							"strand": -1
						},
						{
							"uid": "kmrjuxgfqadpgxwzajvjfhpjefrfhsrkdjps-6",
							"name": "murD",
							"start": 153041,
							"end": 154358,
							"strand": -1
						},
						{
							"uid": "kmrjuxgfqadpgxwzajvjfhpjefrfhsrkdjps-7",
							"name": "mraY",
							"start": 154360,
							"end": 155443,
							"strand": -1
						},
						{
							"uid": "kmrjuxgfqadpgxwzajvjfhpjefrfhsrkdjps-8",
							"name": "murF",
							"start": 155436,
							"end": 156795,
							"strand": -1
						},
						{
							"uid": "kmrjuxgfqadpgxwzajvjfhpjefrfhsrkdjps-9",
							"name": "murE",
							"start": 156791,
							"end": 158279,
							"strand": -1
						},
						{
							"uid": "kmrjuxgfqadpgxwzajvjfhpjefrfhsrkdjps-10",
							"name": "ftsI_2",
							"start": 158265,
							"end": 160032,
							"strand": -1
						},
						{
							"uid": "kmrjuxgfqadpgxwzajvjfhpjefrfhsrkdjps-11",
							"name": "ftsL",
							"start": 160047,
							"end": 160413,
							"strand": -1
						},
						{
							"uid": "kmrjuxgfqadpgxwzajvjfhpjefrfhsrkdjps-12",
							"name": "rsmH",
							"start": 160409,
							"end": 161351,
							"strand": -1
						},
						{
							"uid": "kmrjuxgfqadpgxwzajvjfhpjefrfhsrkdjps-13",
							"name": "mraZ",
							"start": 161352,
							"end": 161811,
							"strand": -1
						},
						{
							"uid": "kmrjuxgfqadpgxwzajvjfhpjefrfhsrkdjps-14",
							"name": "cra",
							"start": 162416,
							"end": 163421,
							"strand": -1
						},
						{
							"uid": "kmrjuxgfqadpgxwzajvjfhpjefrfhsrkdjps-15",
							"name": "ilvH",
							"start": 163704,
							"end": 164199,
							"strand": -1
						},
						{
							"uid": "kmrjuxgfqadpgxwzajvjfhpjefrfhsrkdjps-16",
							"name": "ilvI",
							"start": 164198,
							"end": 165923,
							"strand": -1
						},
						{
							"uid": "kmrjuxgfqadpgxwzajvjfhpjefrfhsrkdjps-17",
							"name": "leuO",
							"start": 166244,
							"end": 167189,
							"strand": -1
						},
						{
							"uid": "kmrjuxgfqadpgxwzajvjfhpjefrfhsrkdjps-18",
							"name": "leuA",
							"start": 168019,
							"end": 169591,
							"strand": 1
						},
						{
							"uid": "kmrjuxgfqadpgxwzajvjfhpjefrfhsrkdjps-19",
							"name": "leuB",
							"start": 169590,
							"end": 170682,
							"strand": 1
						},
						{
							"uid": "kmrjuxgfqadpgxwzajvjfhpjefrfhsrkdjps-20",
							"name": "leuC1",
							"start": 170684,
							"end": 172085,
							"strand": 1
						}
					]
				}
			]
		},
		{
			"uid": "mubrvmykgbtvydxkvqpaiqiaysxohurvdzmt",
			"name": "SA20160200",
			"loci": [
				{
					"uid": "bsbygludomgyeflqopmnlhuillvbywooarwx",
					"name": "SA20160200",
					"start": 227323,
					"end": 253273,
					"genes": [
						{
							"uid": "bsbygludomgyeflqopmnlhuillvbywooarwx-0",
							"name": "leuC1",
							"start": 227323,
							"end": 228724,
							"strand": -1
						},
						{
							"uid": "bsbygludomgyeflqopmnlhuillvbywooarwx-1",
							"name": "leuB",
							"start": 228726,
							"end": 229818,
							"strand": -1
						},
						{
							"uid": "bsbygludomgyeflqopmnlhuillvbywooarwx-2",
							"name": "leuA",
							"start": 229817,
							"end": 231389,
							"strand": -1
						},
						{
							"uid": "bsbygludomgyeflqopmnlhuillvbywooarwx-3",
							"name": "leuO",
							"start": 232219,
							"end": 233164,
							"strand": 1
						},
						{
							"uid": "bsbygludomgyeflqopmnlhuillvbywooarwx-4",
							"name": "ilvI",
							"start": 233485,
							"end": 235210,
							"strand": 1
						},
						{
							"uid": "bsbygludomgyeflqopmnlhuillvbywooarwx-5",
							"name": "ilvH",
							"start": 235209,
							"end": 235704,
							"strand": 1
						},
						{
							"uid": "bsbygludomgyeflqopmnlhuillvbywooarwx-6",
							"name": "cra",
							"start": 235987,
							"end": 236992,
							"strand": 1
						},
						{
							"uid": "bsbygludomgyeflqopmnlhuillvbywooarwx-7",
							"name": "mraZ",
							"start": 237597,
							"end": 238056,
							"strand": 1
						},
						{
							"uid": "bsbygludomgyeflqopmnlhuillvbywooarwx-8",
							"name": "rsmH",
							"start": 238057,
							"end": 238999,
							"strand": 1
						},
						{
							"uid": "bsbygludomgyeflqopmnlhuillvbywooarwx-9",
							"name": "ftsL",
							"start": 238995,
							"end": 239361,
							"strand": 1
						},
						{
							"uid": "bsbygludomgyeflqopmnlhuillvbywooarwx-10",
							"name": "ftsI_2",
							"start": 239376,
							"end": 241143,
							"strand": 1
						},
						{
							"uid": "bsbygludomgyeflqopmnlhuillvbywooarwx-11",
							"name": "murE",
							"start": 241129,
							"end": 242617,
							"strand": 1
						},
						{
							"uid": "bsbygludomgyeflqopmnlhuillvbywooarwx-12",
							"name": "murF",
							"start": 242613,
							"end": 243972,
							"strand": 1
						},
						{
							"uid": "bsbygludomgyeflqopmnlhuillvbywooarwx-13",
							"name": "mraY",
							"start": 243965,
							"end": 245048,
							"strand": 1
						},
						{
							"uid": "bsbygludomgyeflqopmnlhuillvbywooarwx-14",
							"name": "murD",
							"start": 245050,
							"end": 246367,
							"strand": 1
						},
						{
							"uid": "bsbygludomgyeflqopmnlhuillvbywooarwx-15",
							"name": "ftsW",
							"start": 246366,
							"end": 247611,
							"strand": 1
						},
						{
							"uid": "bsbygludomgyeflqopmnlhuillvbywooarwx-16",
							"name": "murG",
							"start": 247607,
							"end": 248675,
							"strand": 1
						},
						{
							"uid": "bsbygludomgyeflqopmnlhuillvbywooarwx-17",
							"name": "murC",
							"start": 248793,
							"end": 250269,
							"strand": 1
						},
						{
							"uid": "bsbygludomgyeflqopmnlhuillvbywooarwx-18",
							"name": "ddlB",
							"start": 250261,
							"end": 251182,
							"strand": 1
						},
						{
							"uid": "bsbygludomgyeflqopmnlhuillvbywooarwx-19",
							"name": "ftsQ",
							"start": 251183,
							"end": 252014,
							"strand": 1
						},
						{
							"uid": "bsbygludomgyeflqopmnlhuillvbywooarwx-20",
							"name": "ftsA_1",
							"start": 252010,
							"end": 253273,
							"strand": 1
						}
					]
				}
			]
		},
		{
			"uid": "dygxosxbsrjyagnvlcrzyftqrpewaneomdrk",
			"name": "SA20160210",
			"loci": [
				{
					"uid": "jknobwuclyybpmnqglhlutlujucjmndtaksa",
					"name": "SA20160210",
					"start": 63343,
					"end": 89293,
					"genes": [
						{
							"uid": "jknobwuclyybpmnqglhlutlujucjmndtaksa-0",
							"name": "leuC1",
							"start": 63343,
							"end": 64744,
							"strand": -1
						},
						{
							"uid": "jknobwuclyybpmnqglhlutlujucjmndtaksa-1",
							"name": "leuB",
							"start": 64746,
							"end": 65838,
							"strand": -1
						},
						{
							"uid": "jknobwuclyybpmnqglhlutlujucjmndtaksa-2",
							"name": "leuA",
							"start": 65837,
							"end": 67409,
							"strand": -1
						},
						{
							"uid": "jknobwuclyybpmnqglhlutlujucjmndtaksa-3",
							"name": "leuO",
							"start": 68239,
							"end": 69184,
							"strand": 1
						},
						{
							"uid": "jknobwuclyybpmnqglhlutlujucjmndtaksa-4",
							"name": "ilvI",
							"start": 69505,
							"end": 71230,
							"strand": 1
						},
						{
							"uid": "jknobwuclyybpmnqglhlutlujucjmndtaksa-5",
							"name": "ilvH",
							"start": 71229,
							"end": 71724,
							"strand": 1
						},
						{
							"uid": "jknobwuclyybpmnqglhlutlujucjmndtaksa-6",
							"name": "cra",
							"start": 72007,
							"end": 73012,
							"strand": 1
						},
						{
							"uid": "jknobwuclyybpmnqglhlutlujucjmndtaksa-7",
							"name": "mraZ",
							"start": 73617,
							"end": 74076,
							"strand": 1
						},
						{
							"uid": "jknobwuclyybpmnqglhlutlujucjmndtaksa-8",
							"name": "rsmH",
							"start": 74077,
							"end": 75019,
							"strand": 1
						},
						{
							"uid": "jknobwuclyybpmnqglhlutlujucjmndtaksa-9",
							"name": "ftsL",
							"start": 75015,
							"end": 75381,
							"strand": 1
						},
						{
							"uid": "jknobwuclyybpmnqglhlutlujucjmndtaksa-10",
							"name": "ftsI_2",
							"start": 75396,
							"end": 77163,
							"strand": 1
						},
						{
							"uid": "jknobwuclyybpmnqglhlutlujucjmndtaksa-11",
							"name": "murE",
							"start": 77149,
							"end": 78637,
							"strand": 1
						},
						{
							"uid": "jknobwuclyybpmnqglhlutlujucjmndtaksa-12",
							"name": "murF",
							"start": 78633,
							"end": 79992,
							"strand": 1
						},
						{
							"uid": "jknobwuclyybpmnqglhlutlujucjmndtaksa-13",
							"name": "mraY",
							"start": 79985,
							"end": 81068,
							"strand": 1
						},
						{
							"uid": "jknobwuclyybpmnqglhlutlujucjmndtaksa-14",
							"name": "murD",
							"start": 81070,
							"end": 82387,
							"strand": 1
						},
						{
							"uid": "jknobwuclyybpmnqglhlutlujucjmndtaksa-15",
							"name": "ftsW",
							"start": 82386,
							"end": 83631,
							"strand": 1
						},
						{
							"uid": "jknobwuclyybpmnqglhlutlujucjmndtaksa-16",
							"name": "murG",
							"start": 83627,
							"end": 84695,
							"strand": 1
						},
						{
							"uid": "jknobwuclyybpmnqglhlutlujucjmndtaksa-17",
							"name": "murC",
							"start": 84813,
							"end": 86289,
							"strand": 1
						},
						{
							"uid": "jknobwuclyybpmnqglhlutlujucjmndtaksa-18",
							"name": "ddlB",
							"start": 86281,
							"end": 87202,
							"strand": 1
						},
						{
							"uid": "jknobwuclyybpmnqglhlutlujucjmndtaksa-19",
							"name": "ftsQ",
							"start": 87203,
							"end": 88034,
							"strand": 1
						},
						{
							"uid": "jknobwuclyybpmnqglhlutlujucjmndtaksa-20",
							"name": "ftsA_1",
							"start": 88030,
							"end": 89293,
							"strand": 1
						}
					]
				}
			]
		},
		{
			"uid": "cmyyjlwzoklkbxygdlgucepwqcpuuyjablcv",
			"name": "SA20160172",
			"loci": [
				{
					"uid": "gzunekavgfjatwafayqhzcjpulgfmbulnnnm",
					"name": "SA20160172",
					"start": 67573,
					"end": 93523,
					"genes": [
						{
							"uid": "gzunekavgfjatwafayqhzcjpulgfmbulnnnm-0",
							"name": "ftsA_2",
							"start": 67573,
							"end": 68836,
							"strand": -1
						},
						{
							"uid": "gzunekavgfjatwafayqhzcjpulgfmbulnnnm-1",
							"name": "ftsQ",
							"start": 68832,
							"end": 69663,
							"strand": -1
						},
						{
							"uid": "gzunekavgfjatwafayqhzcjpulgfmbulnnnm-2",
							"name": "ddlB",
							"start": 69664,
							"end": 70585,
							"strand": -1
						},
						{
							"uid": "gzunekavgfjatwafayqhzcjpulgfmbulnnnm-3",
							"name": "murC",
							"start": 70577,
							"end": 72053,
							"strand": -1
						},
						{
							"uid": "gzunekavgfjatwafayqhzcjpulgfmbulnnnm-4",
							"name": "murG",
							"start": 72171,
							"end": 73239,
							"strand": -1
						},
						{
							"uid": "gzunekavgfjatwafayqhzcjpulgfmbulnnnm-5",
							"name": "ftsW",
							"start": 73235,
							"end": 74480,
							"strand": -1
						},
						{
							"uid": "gzunekavgfjatwafayqhzcjpulgfmbulnnnm-6",
							"name": "murD",
							"start": 74479,
							"end": 75796,
							"strand": -1
						},
						{
							"uid": "gzunekavgfjatwafayqhzcjpulgfmbulnnnm-7",
							"name": "mraY",
							"start": 75798,
							"end": 76881,
							"strand": -1
						},
						{
							"uid": "gzunekavgfjatwafayqhzcjpulgfmbulnnnm-8",
							"name": "murF",
							"start": 76874,
							"end": 78233,
							"strand": -1
						},
						{
							"uid": "gzunekavgfjatwafayqhzcjpulgfmbulnnnm-9",
							"name": "murE",
							"start": 78229,
							"end": 79717,
							"strand": -1
						},
						{
							"uid": "gzunekavgfjatwafayqhzcjpulgfmbulnnnm-10",
							"name": "ftsI_1",
							"start": 79703,
							"end": 81470,
							"strand": -1
						},
						{
							"uid": "gzunekavgfjatwafayqhzcjpulgfmbulnnnm-11",
							"name": "ftsL",
							"start": 81485,
							"end": 81851,
							"strand": -1
						},
						{
							"uid": "gzunekavgfjatwafayqhzcjpulgfmbulnnnm-12",
							"name": "rsmH",
							"start": 81847,
							"end": 82789,
							"strand": -1
						},
						{
							"uid": "gzunekavgfjatwafayqhzcjpulgfmbulnnnm-13",
							"name": "mraZ",
							"start": 82790,
							"end": 83249,
							"strand": -1
						},
						{
							"uid": "gzunekavgfjatwafayqhzcjpulgfmbulnnnm-14",
							"name": "cra",
							"start": 83854,
							"end": 84859,
							"strand": -1
						},
						{
							"uid": "gzunekavgfjatwafayqhzcjpulgfmbulnnnm-15",
							"name": "ilvH",
							"start": 85142,
							"end": 85637,
							"strand": -1
						},
						{
							"uid": "gzunekavgfjatwafayqhzcjpulgfmbulnnnm-16",
							"name": "ilvI",
							"start": 85636,
							"end": 87361,
							"strand": -1
						},
						{
							"uid": "gzunekavgfjatwafayqhzcjpulgfmbulnnnm-17",
							"name": "leuO",
							"start": 87682,
							"end": 88627,
							"strand": -1
						},
						{
							"uid": "gzunekavgfjatwafayqhzcjpulgfmbulnnnm-18",
							"name": "leuA",
							"start": 89457,
							"end": 91029,
							"strand": 1
						},
						{
							"uid": "gzunekavgfjatwafayqhzcjpulgfmbulnnnm-19",
							"name": "leuB",
							"start": 91028,
							"end": 92120,
							"strand": 1
						},
						{
							"uid": "gzunekavgfjatwafayqhzcjpulgfmbulnnnm-20",
							"name": "leuC1",
							"start": 92122,
							"end": 93523,
							"strand": 1
						}
					]
				}
			]
		},
		{
			"uid": "dggsfflyaryhngugpggiihtahieeaxjscwhw",
			"name": "SA20153980",
			"loci": [
				{
					"uid": "pakbnqtpnrbuwizuhgznbxpgdwzfhqoonvfh",
					"name": "SA20153980",
					"start": 63340,
					"end": 89290,
					"genes": [
						{
							"uid": "pakbnqtpnrbuwizuhgznbxpgdwzfhqoonvfh-0",
							"name": "leuC1",
							"start": 63340,
							"end": 64741,
							"strand": -1
						},
						{
							"uid": "pakbnqtpnrbuwizuhgznbxpgdwzfhqoonvfh-1",
							"name": "leuB",
							"start": 64743,
							"end": 65835,
							"strand": -1
						},
						{
							"uid": "pakbnqtpnrbuwizuhgznbxpgdwzfhqoonvfh-2",
							"name": "leuA",
							"start": 65834,
							"end": 67406,
							"strand": -1
						},
						{
							"uid": "pakbnqtpnrbuwizuhgznbxpgdwzfhqoonvfh-3",
							"name": "leuO",
							"start": 68236,
							"end": 69181,
							"strand": 1
						},
						{
							"uid": "pakbnqtpnrbuwizuhgznbxpgdwzfhqoonvfh-4",
							"name": "ilvI",
							"start": 69502,
							"end": 71227,
							"strand": 1
						},
						{
							"uid": "pakbnqtpnrbuwizuhgznbxpgdwzfhqoonvfh-5",
							"name": "ilvH",
							"start": 71226,
							"end": 71721,
							"strand": 1
						},
						{
							"uid": "pakbnqtpnrbuwizuhgznbxpgdwzfhqoonvfh-6",
							"name": "cra",
							"start": 72004,
							"end": 73009,
							"strand": 1
						},
						{
							"uid": "pakbnqtpnrbuwizuhgznbxpgdwzfhqoonvfh-7",
							"name": "mraZ",
							"start": 73614,
							"end": 74073,
							"strand": 1
						},
						{
							"uid": "pakbnqtpnrbuwizuhgznbxpgdwzfhqoonvfh-8",
							"name": "rsmH",
							"start": 74074,
							"end": 75016,
							"strand": 1
						},
						{
							"uid": "pakbnqtpnrbuwizuhgznbxpgdwzfhqoonvfh-9",
							"name": "ftsL",
							"start": 75012,
							"end": 75378,
							"strand": 1
						},
						{
							"uid": "pakbnqtpnrbuwizuhgznbxpgdwzfhqoonvfh-10",
							"name": "ftsI_2",
							"start": 75393,
							"end": 77160,
							"strand": 1
						},
						{
							"uid": "pakbnqtpnrbuwizuhgznbxpgdwzfhqoonvfh-11",
							"name": "murE",
							"start": 77146,
							"end": 78634,
							"strand": 1
						},
						{
							"uid": "pakbnqtpnrbuwizuhgznbxpgdwzfhqoonvfh-12",
							"name": "murF",
							"start": 78630,
							"end": 79989,
							"strand": 1
						},
						{
							"uid": "pakbnqtpnrbuwizuhgznbxpgdwzfhqoonvfh-13",
							"name": "mraY",
							"start": 79982,
							"end": 81065,
							"strand": 1
						},
						{
							"uid": "pakbnqtpnrbuwizuhgznbxpgdwzfhqoonvfh-14",
							"name": "murD",
							"start": 81067,
							"end": 82384,
							"strand": 1
						},
						{
							"uid": "pakbnqtpnrbuwizuhgznbxpgdwzfhqoonvfh-15",
							"name": "ftsW",
							"start": 82383,
							"end": 83628,
							"strand": 1
						},
						{
							"uid": "pakbnqtpnrbuwizuhgznbxpgdwzfhqoonvfh-16",
							"name": "murG",
							"start": 83624,
							"end": 84692,
							"strand": 1
						},
						{
							"uid": "pakbnqtpnrbuwizuhgznbxpgdwzfhqoonvfh-17",
							"name": "murC",
							"start": 84810,
							"end": 86286,
							"strand": 1
						},
						{
							"uid": "pakbnqtpnrbuwizuhgznbxpgdwzfhqoonvfh-18",
							"name": "ddlB",
							"start": 86278,
							"end": 87199,
							"strand": 1
						},
						{
							"uid": "pakbnqtpnrbuwizuhgznbxpgdwzfhqoonvfh-19",
							"name": "ftsQ",
							"start": 87200,
							"end": 88031,
							"strand": 1
						},
						{
							"uid": "pakbnqtpnrbuwizuhgznbxpgdwzfhqoonvfh-20",
							"name": "ftsA_1",
							"start": 88027,
							"end": 89290,
							"strand": 1
						}
					]
				}
			]
		},
		{
			"uid": "etiraiuadcrqndbdssjgcdpwajivliobarpe",
			"name": "SA20160190",
			"loci": [
				{
					"uid": "hfuxzlhqzyeisilfflfwqopvsityozsqcwum",
					"name": "SA20160190",
					"start": 63571,
					"end": 89520,
					"genes": [
						{
							"uid": "hfuxzlhqzyeisilfflfwqopvsityozsqcwum-0",
							"name": "leuC1",
							"start": 63571,
							"end": 64972,
							"strand": -1
						},
						{
							"uid": "hfuxzlhqzyeisilfflfwqopvsityozsqcwum-1",
							"name": "leuB",
							"start": 64974,
							"end": 66066,
							"strand": -1
						},
						{
							"uid": "hfuxzlhqzyeisilfflfwqopvsityozsqcwum-2",
							"name": "leuA",
							"start": 66065,
							"end": 67637,
							"strand": -1
						},
						{
							"uid": "hfuxzlhqzyeisilfflfwqopvsityozsqcwum-3",
							"name": "leuO",
							"start": 68467,
							"end": 69412,
							"strand": 1
						},
						{
							"uid": "hfuxzlhqzyeisilfflfwqopvsityozsqcwum-4",
							"name": "ilvI",
							"start": 69733,
							"end": 71458,
							"strand": 1
						},
						{
							"uid": "hfuxzlhqzyeisilfflfwqopvsityozsqcwum-5",
							"name": "ilvH",
							"start": 71457,
							"end": 71952,
							"strand": 1
						},
						{
							"uid": "hfuxzlhqzyeisilfflfwqopvsityozsqcwum-6",
							"name": "cra",
							"start": 72234,
							"end": 73239,
							"strand": 1
						},
						{
							"uid": "hfuxzlhqzyeisilfflfwqopvsityozsqcwum-7",
							"name": "mraZ",
							"start": 73844,
							"end": 74303,
							"strand": 1
						},
						{
							"uid": "hfuxzlhqzyeisilfflfwqopvsityozsqcwum-8",
							"name": "rsmH",
							"start": 74304,
							"end": 75246,
							"strand": 1
						},
						{
							"uid": "hfuxzlhqzyeisilfflfwqopvsityozsqcwum-9",
							"name": "ftsL",
							"start": 75242,
							"end": 75608,
							"strand": 1
						},
						{
							"uid": "hfuxzlhqzyeisilfflfwqopvsityozsqcwum-10",
							"name": "ftsI_2",
							"start": 75623,
							"end": 77390,
							"strand": 1
						},
						{
							"uid": "hfuxzlhqzyeisilfflfwqopvsityozsqcwum-11",
							"name": "murE",
							"start": 77376,
							"end": 78864,
							"strand": 1
						},
						{
							"uid": "hfuxzlhqzyeisilfflfwqopvsityozsqcwum-12",
							"name": "murF",
							"start": 78860,
							"end": 80219,
							"strand": 1
						},
						{
							"uid": "hfuxzlhqzyeisilfflfwqopvsityozsqcwum-13",
							"name": "mraY",
							"start": 80212,
							"end": 81295,
							"strand": 1
						},
						{
							"uid": "hfuxzlhqzyeisilfflfwqopvsityozsqcwum-14",
							"name": "murD",
							"start": 81297,
							"end": 82614,
							"strand": 1
						},
						{
							"uid": "hfuxzlhqzyeisilfflfwqopvsityozsqcwum-15",
							"name": "ftsW",
							"start": 82613,
							"end": 83858,
							"strand": 1
						},
						{
							"uid": "hfuxzlhqzyeisilfflfwqopvsityozsqcwum-16",
							"name": "murG",
							"start": 83854,
							"end": 84922,
							"strand": 1
						},
						{
							"uid": "hfuxzlhqzyeisilfflfwqopvsityozsqcwum-17",
							"name": "murC",
							"start": 85040,
							"end": 86516,
							"strand": 1
						},
						{
							"uid": "hfuxzlhqzyeisilfflfwqopvsityozsqcwum-18",
							"name": "ddlB",
							"start": 86508,
							"end": 87429,
							"strand": 1
						},
						{
							"uid": "hfuxzlhqzyeisilfflfwqopvsityozsqcwum-19",
							"name": "ftsQ",
							"start": 87430,
							"end": 88261,
							"strand": 1
						},
						{
							"uid": "hfuxzlhqzyeisilfflfwqopvsityozsqcwum-20",
							"name": "ftsA_2",
							"start": 88257,
							"end": 89520,
							"strand": 1
						}
					]
				}
			]
		}
	],
	"links": [
		},
		{
			"uid": "link1",
			"target": {
				"uid": "pakbnqtpnrbuwizuhgznbxpgdwzfhqoonvfh-19",
				"name": "ftsQ-1"
			},
			"query": {
				"uid": "hfuxzlhqzyeisilfflfwqopvsityozsqcwum-19",
				"name": "ftsQ-2"
			},
			"identity": "0.5"
		},
		{
			"uid": "link2",
			"target": {
				"uid": "pakbnqtpnrbuwizuhgznbxpgdwzfhqoonvfh-18",
				"name": "ddlB-1"
			},
			"query": {
				"uid": "hfuxzlhqzyeisilfflfwqopvsityozsqcwum-18",
				"name": "ddlB-2"
			},
			"identity": "0.5"
		},
		{
			"uid": "link3",
			"target": {
				"uid": "pakbnqtpnrbuwizuhgznbxpgdwzfhqoonvfh-17",
				"name": "murC-1"
			},
			"query": {
				"uid": "hfuxzlhqzyeisilfflfwqopvsityozsqcwum-17",
				"name": "murC-2"
			},
			"identity": "0.5"
		},
		{
			"uid": "link4",
			"target": {
				"uid": "pakbnqtpnrbuwizuhgznbxpgdwzfhqoonvfh-16",
				"name": "murG-1"
			},
			"query": {
				"uid": "hfuxzlhqzyeisilfflfwqopvsityozsqcwum-16",
				"name": "murG-2"
			},
			"identity": "0.5"
		},
		{
			"uid": "link5",
			"target": {
				"uid": "pakbnqtpnrbuwizuhgznbxpgdwzfhqoonvfh-15",
				"name": "ftsW-1"
			},
			"query": {
				"uid": "hfuxzlhqzyeisilfflfwqopvsityozsqcwum-15",
				"name": "ftsW-2"
			},
			"identity": "0.5"
		},
		{
			"uid": "link6",
			"target": {
				"uid": "pakbnqtpnrbuwizuhgznbxpgdwzfhqoonvfh-14",
				"name": "murD-1"
			},
			"query": {
				"uid": "hfuxzlhqzyeisilfflfwqopvsityozsqcwum-14",
				"name": "murD-2"
			},
			"identity": "0.5"
		},
		{
			"uid": "link7",
			"target": {
				"uid": "pakbnqtpnrbuwizuhgznbxpgdwzfhqoonvfh-13",
				"name": "mraY-1"
			},
			"query": {
				"uid": "hfuxzlhqzyeisilfflfwqopvsityozsqcwum-13",
				"name": "mraY-2"
			},
			"identity": "0.5"
		},
		{
			"uid": "link8",
			"target": {
				"uid": "pakbnqtpnrbuwizuhgznbxpgdwzfhqoonvfh-12",
				"name": "murF-1"
			},
			"query": {
				"uid": "hfuxzlhqzyeisilfflfwqopvsityozsqcwum-12",
				"name": "murF-2"
			},
			"identity": "0.5"
		},
		{
			"uid": "link9",
			"target": {
				"uid": "pakbnqtpnrbuwizuhgznbxpgdwzfhqoonvfh-11",
				"name": "murE-1"
			},
			"query": {
				"uid": "hfuxzlhqzyeisilfflfwqopvsityozsqcwum-11",
				"name": "murE-2"
			},
			"identity": "0.5"
		},
		{
			"uid": "link10",
			"target": {
				"uid": "pakbnqtpnrbuwizuhgznbxpgdwzfhqoonvfh-10",
				"name": "ftsI_2-1"
			},
			"query": {
				"uid": "hfuxzlhqzyeisilfflfwqopvsityozsqcwum-10",
				"name": "ftsI_2-2"
			},
			"identity": "0.5"
		},
		{
			"uid": "link11",
			"target": {
				"uid": "pakbnqtpnrbuwizuhgznbxpgdwzfhqoonvfh-9",
				"name": "ftsL-1"
			},
			"query": {
				"uid": "hfuxzlhqzyeisilfflfwqopvsityozsqcwum-9",
				"name": "ftsL-2"
			},
			"identity": "0.5"
		},
		{
			"uid": "link12",
			"target": {
				"uid": "pakbnqtpnrbuwizuhgznbxpgdwzfhqoonvfh-8",
				"name": "rsmH-1"
			},
			"query": {
				"uid": "hfuxzlhqzyeisilfflfwqopvsityozsqcwum-8",
				"name": "rsmH-2"
			},
			"identity": "0.5"
		},
		{
			"uid": "link13",
			"target": {
				"uid": "pakbnqtpnrbuwizuhgznbxpgdwzfhqoonvfh-7",
				"name": "mraZ-1"
			},
			"query": {
				"uid": "hfuxzlhqzyeisilfflfwqopvsityozsqcwum-7",
				"name": "mraZ-2"
			},
			"identity": "0.5"
		},
		{
			"uid": "link14",
			"target": {
				"uid": "pakbnqtpnrbuwizuhgznbxpgdwzfhqoonvfh-6",
				"name": "cra-1"
			},
			"query": {
				"uid": "hfuxzlhqzyeisilfflfwqopvsityozsqcwum-6",
				"name": "cra-2"
			},
			"identity": "0.5"
		},
		{
			"uid": "link15",
			"target": {
				"uid": "pakbnqtpnrbuwizuhgznbxpgdwzfhqoonvfh-5",
				"name": "ilvH-1"
			},
			"query": {
				"uid": "hfuxzlhqzyeisilfflfwqopvsityozsqcwum-5",
				"name": "ilvH-2"
			},
			"identity": "0.5"
		},
		{
			"uid": "link16",
			"target": {
				"uid": "pakbnqtpnrbuwizuhgznbxpgdwzfhqoonvfh-4",
				"name": "ilvI-1"
			},
			"query": {
				"uid": "hfuxzlhqzyeisilfflfwqopvsityozsqcwum-4",
				"name": "ilvI-2"
			},
			"identity": "0.5"
		},
		},
		{
			"uid": "link18",
			"target": {
				"uid": "pakbnqtpnrbuwizuhgznbxpgdwzfhqoonvfh-2",
				"name": "leuA-1"
			},
			"query": {
				"uid": "hfuxzlhqzyeisilfflfwqopvsityozsqcwum-2",
				"name": "leuA-2"
			},
			"identity": "0.5"
		},
		{
			"uid": "link19",
			"target": {
				"uid": "pakbnqtpnrbuwizuhgznbxpgdwzfhqoonvfh-1",
				"name": "leuB-1"
			},
			"query": {
				"uid": "hfuxzlhqzyeisilfflfwqopvsityozsqcwum-1",
				"name": "leuB-2"
			},
			"identity": "0.5"
		},
		{
			"uid": "link20",
			"target": {
				"uid": "pakbnqtpnrbuwizuhgznbxpgdwzfhqoonvfh-0",
				"name": "leuC1-1"
			},
			"query": {
				"uid": "hfuxzlhqzyeisilfflfwqopvsityozsqcwum-0",
				"name": "leuC1-2"
			},
			"identity": "0.5"
		},
		{
			"uid": "link21",
			"target": {
				"uid": "pakbnqtpnrbuwizuhgznbxpgdwzfhqoonvfh-3",
				"name": "leuO-1"
			},
			"query": {
				"uid": "hfuxzlhqzyeisilfflfwqopvsityozsqcwum-3",
				"name": "leuO-2"
			},
			"identity": "0.5"
		},
		},
		}
	],
	"groups": [
		{
			"uid": "group0",
			"label": "ftsA_2",
			"genes": ["syzazxvdjgbnnqrsoxdlbmvhdlvwjbwhohpb-0", "fibnrjmrupgbvqncwcspjxlfdqdbqwvuesum-20", "srhwliukqgwasifxrnnjmlxxipiqietrykhi-0", "lzezkmktpaooltqqxjjshhwuwzvqgatfnyhk-0", "gzunekavgfjatwafayqhzcjpulgfmbulnnnm-0", "hfuxzlhqzyeisilfflfwqopvsityozsqcwum-20"]
		},
		{
			"uid": "group1",
			"label": "ftsQ",
			"genes": ["syzazxvdjgbnnqrsoxdlbmvhdlvwjbwhohpb-1", "shncgijylmrzyxngguztabvawkcocibthsit-19", "kokqyqyrupwkmphgvafeziybldkujwrmqstx-19", "fibnrjmrupgbvqncwcspjxlfdqdbqwvuesum-19", "tmbumlpqopzbkiqwcnzbysiajbveyatjqchf-1", "lkmhkflfaiuhikosucymdifroqxdkhoupifr-19", "srhwliukqgwasifxrnnjmlxxipiqietrykhi-1", "lzezkmktpaooltqqxjjshhwuwzvqgatfnyhk-1", "kmrjuxgfqadpgxwzajvjfhpjefrfhsrkdjps-1", "bsbygludomgyeflqopmnlhuillvbywooarwx-19", "jknobwuclyybpmnqglhlutlujucjmndtaksa-19", "gzunekavgfjatwafayqhzcjpulgfmbulnnnm-1", "pakbnqtpnrbuwizuhgznbxpgdwzfhqoonvfh-19", "hfuxzlhqzyeisilfflfwqopvsityozsqcwum-19"]
		},
		{
			"uid": "group2",
			"label": "ddlB",
			"genes": ["syzazxvdjgbnnqrsoxdlbmvhdlvwjbwhohpb-2", "shncgijylmrzyxngguztabvawkcocibthsit-18", "kokqyqyrupwkmphgvafeziybldkujwrmqstx-18", "fibnrjmrupgbvqncwcspjxlfdqdbqwvuesum-18", "tmbumlpqopzbkiqwcnzbysiajbveyatjqchf-2", "lkmhkflfaiuhikosucymdifroqxdkhoupifr-18", "srhwliukqgwasifxrnnjmlxxipiqietrykhi-2", "lzezkmktpaooltqqxjjshhwuwzvqgatfnyhk-2", "kmrjuxgfqadpgxwzajvjfhpjefrfhsrkdjps-2", "bsbygludomgyeflqopmnlhuillvbywooarwx-18", "jknobwuclyybpmnqglhlutlujucjmndtaksa-18", "gzunekavgfjatwafayqhzcjpulgfmbulnnnm-2", "pakbnqtpnrbuwizuhgznbxpgdwzfhqoonvfh-18", "hfuxzlhqzyeisilfflfwqopvsityozsqcwum-18"]
		},
		{
			"uid": "group3",
			"label": "murC",
			"genes": ["syzazxvdjgbnnqrsoxdlbmvhdlvwjbwhohpb-3", "shncgijylmrzyxngguztabvawkcocibthsit-17", "kokqyqyrupwkmphgvafeziybldkujwrmqstx-17", "fibnrjmrupgbvqncwcspjxlfdqdbqwvuesum-17", "tmbumlpqopzbkiqwcnzbysiajbveyatjqchf-3", "lkmhkflfaiuhikosucymdifroqxdkhoupifr-17", "srhwliukqgwasifxrnnjmlxxipiqietrykhi-3", "lzezkmktpaooltqqxjjshhwuwzvqgatfnyhk-3", "kmrjuxgfqadpgxwzajvjfhpjefrfhsrkdjps-3", "bsbygludomgyeflqopmnlhuillvbywooarwx-17", "jknobwuclyybpmnqglhlutlujucjmndtaksa-17", "gzunekavgfjatwafayqhzcjpulgfmbulnnnm-3", "pakbnqtpnrbuwizuhgznbxpgdwzfhqoonvfh-17", "hfuxzlhqzyeisilfflfwqopvsityozsqcwum-17"]
		},
		{
			"uid": "group4",
			"label": "murG",
			"genes": ["syzazxvdjgbnnqrsoxdlbmvhdlvwjbwhohpb-4", "shncgijylmrzyxngguztabvawkcocibthsit-16", "kokqyqyrupwkmphgvafeziybldkujwrmqstx-16", "fibnrjmrupgbvqncwcspjxlfdqdbqwvuesum-16", "tmbumlpqopzbkiqwcnzbysiajbveyatjqchf-4", "lkmhkflfaiuhikosucymdifroqxdkhoupifr-16", "srhwliukqgwasifxrnnjmlxxipiqietrykhi-4", "lzezkmktpaooltqqxjjshhwuwzvqgatfnyhk-4", "kmrjuxgfqadpgxwzajvjfhpjefrfhsrkdjps-4", "bsbygludomgyeflqopmnlhuillvbywooarwx-16", "jknobwuclyybpmnqglhlutlujucjmndtaksa-16", "gzunekavgfjatwafayqhzcjpulgfmbulnnnm-4", "pakbnqtpnrbuwizuhgznbxpgdwzfhqoonvfh-16", "hfuxzlhqzyeisilfflfwqopvsityozsqcwum-16"]
		},
		{
			"uid": "group5",
			"label": "ftsW",
			"genes": ["syzazxvdjgbnnqrsoxdlbmvhdlvwjbwhohpb-5", "shncgijylmrzyxngguztabvawkcocibthsit-15", "kokqyqyrupwkmphgvafeziybldkujwrmqstx-15", "fibnrjmrupgbvqncwcspjxlfdqdbqwvuesum-15", "tmbumlpqopzbkiqwcnzbysiajbveyatjqchf-5", "lkmhkflfaiuhikosucymdifroqxdkhoupifr-15", "srhwliukqgwasifxrnnjmlxxipiqietrykhi-5", "lzezkmktpaooltqqxjjshhwuwzvqgatfnyhk-5", "kmrjuxgfqadpgxwzajvjfhpjefrfhsrkdjps-5", "bsbygludomgyeflqopmnlhuillvbywooarwx-15", "jknobwuclyybpmnqglhlutlujucjmndtaksa-15", "gzunekavgfjatwafayqhzcjpulgfmbulnnnm-5", "pakbnqtpnrbuwizuhgznbxpgdwzfhqoonvfh-15", "hfuxzlhqzyeisilfflfwqopvsityozsqcwum-15"]
		},
		{
			"uid": "group6",
			"label": "murD",
			"genes": ["syzazxvdjgbnnqrsoxdlbmvhdlvwjbwhohpb-6", "shncgijylmrzyxngguztabvawkcocibthsit-14", "kokqyqyrupwkmphgvafeziybldkujwrmqstx-14", "fibnrjmrupgbvqncwcspjxlfdqdbqwvuesum-14", "tmbumlpqopzbkiqwcnzbysiajbveyatjqchf-6", "lkmhkflfaiuhikosucymdifroqxdkhoupifr-14", "srhwliukqgwasifxrnnjmlxxipiqietrykhi-6", "lzezkmktpaooltqqxjjshhwuwzvqgatfnyhk-6", "kmrjuxgfqadpgxwzajvjfhpjefrfhsrkdjps-6", "bsbygludomgyeflqopmnlhuillvbywooarwx-14", "jknobwuclyybpmnqglhlutlujucjmndtaksa-14", "gzunekavgfjatwafayqhzcjpulgfmbulnnnm-6", "pakbnqtpnrbuwizuhgznbxpgdwzfhqoonvfh-14", "hfuxzlhqzyeisilfflfwqopvsityozsqcwum-14"]
		},
		{
			"uid": "group7",
			"label": "mraY",
			"genes": ["syzazxvdjgbnnqrsoxdlbmvhdlvwjbwhohpb-7", "shncgijylmrzyxngguztabvawkcocibthsit-13", "kokqyqyrupwkmphgvafeziybldkujwrmqstx-13", "fibnrjmrupgbvqncwcspjxlfdqdbqwvuesum-13", "tmbumlpqopzbkiqwcnzbysiajbveyatjqchf-7", "lkmhkflfaiuhikosucymdifroqxdkhoupifr-13", "srhwliukqgwasifxrnnjmlxxipiqietrykhi-7", "lzezkmktpaooltqqxjjshhwuwzvqgatfnyhk-7", "kmrjuxgfqadpgxwzajvjfhpjefrfhsrkdjps-7", "bsbygludomgyeflqopmnlhuillvbywooarwx-13", "jknobwuclyybpmnqglhlutlujucjmndtaksa-13", "gzunekavgfjatwafayqhzcjpulgfmbulnnnm-7", "pakbnqtpnrbuwizuhgznbxpgdwzfhqoonvfh-13", "hfuxzlhqzyeisilfflfwqopvsityozsqcwum-13"]
		},
		{
			"uid": "group8",
			"label": "murF",
			"genes": ["syzazxvdjgbnnqrsoxdlbmvhdlvwjbwhohpb-8", "shncgijylmrzyxngguztabvawkcocibthsit-12", "kokqyqyrupwkmphgvafeziybldkujwrmqstx-12", "fibnrjmrupgbvqncwcspjxlfdqdbqwvuesum-12", "tmbumlpqopzbkiqwcnzbysiajbveyatjqchf-8", "lkmhkflfaiuhikosucymdifroqxdkhoupifr-12", "srhwliukqgwasifxrnnjmlxxipiqietrykhi-8", "lzezkmktpaooltqqxjjshhwuwzvqgatfnyhk-8", "kmrjuxgfqadpgxwzajvjfhpjefrfhsrkdjps-8", "bsbygludomgyeflqopmnlhuillvbywooarwx-12", "jknobwuclyybpmnqglhlutlujucjmndtaksa-12", "gzunekavgfjatwafayqhzcjpulgfmbulnnnm-8", "pakbnqtpnrbuwizuhgznbxpgdwzfhqoonvfh-12", "hfuxzlhqzyeisilfflfwqopvsityozsqcwum-12"]
		},
		{
			"uid": "group9",
			"label": "murE",
			"genes": ["syzazxvdjgbnnqrsoxdlbmvhdlvwjbwhohpb-9", "shncgijylmrzyxngguztabvawkcocibthsit-11", "kokqyqyrupwkmphgvafeziybldkujwrmqstx-11", "fibnrjmrupgbvqncwcspjxlfdqdbqwvuesum-11", "tmbumlpqopzbkiqwcnzbysiajbveyatjqchf-9", "lkmhkflfaiuhikosucymdifroqxdkhoupifr-11", "srhwliukqgwasifxrnnjmlxxipiqietrykhi-9", "lzezkmktpaooltqqxjjshhwuwzvqgatfnyhk-9", "kmrjuxgfqadpgxwzajvjfhpjefrfhsrkdjps-9", "bsbygludomgyeflqopmnlhuillvbywooarwx-11", "jknobwuclyybpmnqglhlutlujucjmndtaksa-11", "gzunekavgfjatwafayqhzcjpulgfmbulnnnm-9", "pakbnqtpnrbuwizuhgznbxpgdwzfhqoonvfh-11", "hfuxzlhqzyeisilfflfwqopvsityozsqcwum-11"]
		},
		{
			"uid": "group10",
			"label": "ftsI_2",
			"genes": ["syzazxvdjgbnnqrsoxdlbmvhdlvwjbwhohpb-10", "shncgijylmrzyxngguztabvawkcocibthsit-10", "kokqyqyrupwkmphgvafeziybldkujwrmqstx-10", "fibnrjmrupgbvqncwcspjxlfdqdbqwvuesum-10", "lkmhkflfaiuhikosucymdifroqxdkhoupifr-10", "lzezkmktpaooltqqxjjshhwuwzvqgatfnyhk-10", "kmrjuxgfqadpgxwzajvjfhpjefrfhsrkdjps-10", "bsbygludomgyeflqopmnlhuillvbywooarwx-10", "jknobwuclyybpmnqglhlutlujucjmndtaksa-10", "pakbnqtpnrbuwizuhgznbxpgdwzfhqoonvfh-10", "hfuxzlhqzyeisilfflfwqopvsityozsqcwum-10"]
		},
		{
			"uid": "group11",
			"label": "ftsL",
			"genes": ["syzazxvdjgbnnqrsoxdlbmvhdlvwjbwhohpb-11", "shncgijylmrzyxngguztabvawkcocibthsit-9", "kokqyqyrupwkmphgvafeziybldkujwrmqstx-9", "fibnrjmrupgbvqncwcspjxlfdqdbqwvuesum-9", "tmbumlpqopzbkiqwcnzbysiajbveyatjqchf-11", "lkmhkflfaiuhikosucymdifroqxdkhoupifr-9", "srhwliukqgwasifxrnnjmlxxipiqietrykhi-11", "lzezkmktpaooltqqxjjshhwuwzvqgatfnyhk-11", "kmrjuxgfqadpgxwzajvjfhpjefrfhsrkdjps-11", "bsbygludomgyeflqopmnlhuillvbywooarwx-9", "jknobwuclyybpmnqglhlutlujucjmndtaksa-9", "gzunekavgfjatwafayqhzcjpulgfmbulnnnm-11", "pakbnqtpnrbuwizuhgznbxpgdwzfhqoonvfh-9", "hfuxzlhqzyeisilfflfwqopvsityozsqcwum-9"]
		},
		{
			"uid": "group12",
			"label": "rsmH",
			"genes": ["syzazxvdjgbnnqrsoxdlbmvhdlvwjbwhohpb-12", "shncgijylmrzyxngguztabvawkcocibthsit-8", "kokqyqyrupwkmphgvafeziybldkujwrmqstx-8", "fibnrjmrupgbvqncwcspjxlfdqdbqwvuesum-8", "tmbumlpqopzbkiqwcnzbysiajbveyatjqchf-12", "lkmhkflfaiuhikosucymdifroqxdkhoupifr-8", "srhwliukqgwasifxrnnjmlxxipiqietrykhi-12", "lzezkmktpaooltqqxjjshhwuwzvqgatfnyhk-12", "kmrjuxgfqadpgxwzajvjfhpjefrfhsrkdjps-12", "bsbygludomgyeflqopmnlhuillvbywooarwx-8", "jknobwuclyybpmnqglhlutlujucjmndtaksa-8", "gzunekavgfjatwafayqhzcjpulgfmbulnnnm-12", "pakbnqtpnrbuwizuhgznbxpgdwzfhqoonvfh-8", "hfuxzlhqzyeisilfflfwqopvsityozsqcwum-8"]
		},
		{
			"uid": "group13",
			"label": "mraZ",
			"genes": ["syzazxvdjgbnnqrsoxdlbmvhdlvwjbwhohpb-13", "shncgijylmrzyxngguztabvawkcocibthsit-7", "kokqyqyrupwkmphgvafeziybldkujwrmqstx-7", "fibnrjmrupgbvqncwcspjxlfdqdbqwvuesum-7", "tmbumlpqopzbkiqwcnzbysiajbveyatjqchf-13", "lkmhkflfaiuhikosucymdifroqxdkhoupifr-7", "srhwliukqgwasifxrnnjmlxxipiqietrykhi-13", "lzezkmktpaooltqqxjjshhwuwzvqgatfnyhk-13", "kmrjuxgfqadpgxwzajvjfhpjefrfhsrkdjps-13", "bsbygludomgyeflqopmnlhuillvbywooarwx-7", "jknobwuclyybpmnqglhlutlujucjmndtaksa-7", "gzunekavgfjatwafayqhzcjpulgfmbulnnnm-13", "pakbnqtpnrbuwizuhgznbxpgdwzfhqoonvfh-7", "hfuxzlhqzyeisilfflfwqopvsityozsqcwum-7"]
		},
		{
			"uid": "group14",
			"label": "cra",
			"genes": ["syzazxvdjgbnnqrsoxdlbmvhdlvwjbwhohpb-14", "shncgijylmrzyxngguztabvawkcocibthsit-6", "kokqyqyrupwkmphgvafeziybldkujwrmqstx-6", "fibnrjmrupgbvqncwcspjxlfdqdbqwvuesum-6", "tmbumlpqopzbkiqwcnzbysiajbveyatjqchf-14", "lkmhkflfaiuhikosucymdifroqxdkhoupifr-6", "srhwliukqgwasifxrnnjmlxxipiqietrykhi-14", "lzezkmktpaooltqqxjjshhwuwzvqgatfnyhk-14", "kmrjuxgfqadpgxwzajvjfhpjefrfhsrkdjps-14", "bsbygludomgyeflqopmnlhuillvbywooarwx-6", "jknobwuclyybpmnqglhlutlujucjmndtaksa-6", "gzunekavgfjatwafayqhzcjpulgfmbulnnnm-14", "pakbnqtpnrbuwizuhgznbxpgdwzfhqoonvfh-6", "hfuxzlhqzyeisilfflfwqopvsityozsqcwum-6"]
		},
		{
			"uid": "group15",
			"label": "ilvH",
			"genes": ["syzazxvdjgbnnqrsoxdlbmvhdlvwjbwhohpb-15", "shncgijylmrzyxngguztabvawkcocibthsit-5", "kokqyqyrupwkmphgvafeziybldkujwrmqstx-5", "fibnrjmrupgbvqncwcspjxlfdqdbqwvuesum-5", "tmbumlpqopzbkiqwcnzbysiajbveyatjqchf-15", "lkmhkflfaiuhikosucymdifroqxdkhoupifr-5", "srhwliukqgwasifxrnnjmlxxipiqietrykhi-15", "lzezkmktpaooltqqxjjshhwuwzvqgatfnyhk-15", "kmrjuxgfqadpgxwzajvjfhpjefrfhsrkdjps-15", "bsbygludomgyeflqopmnlhuillvbywooarwx-5", "jknobwuclyybpmnqglhlutlujucjmndtaksa-5", "gzunekavgfjatwafayqhzcjpulgfmbulnnnm-15", "pakbnqtpnrbuwizuhgznbxpgdwzfhqoonvfh-5", "hfuxzlhqzyeisilfflfwqopvsityozsqcwum-5"]
		},
		{
			"uid": "group16",
			"label": "ilvI",
			"genes": ["syzazxvdjgbnnqrsoxdlbmvhdlvwjbwhohpb-16", "shncgijylmrzyxngguztabvawkcocibthsit-4", "kokqyqyrupwkmphgvafeziybldkujwrmqstx-4", "fibnrjmrupgbvqncwcspjxlfdqdbqwvuesum-4", "tmbumlpqopzbkiqwcnzbysiajbveyatjqchf-16", "lkmhkflfaiuhikosucymdifroqxdkhoupifr-4", "srhwliukqgwasifxrnnjmlxxipiqietrykhi-16", "lzezkmktpaooltqqxjjshhwuwzvqgatfnyhk-16", "kmrjuxgfqadpgxwzajvjfhpjefrfhsrkdjps-16", "bsbygludomgyeflqopmnlhuillvbywooarwx-4", "jknobwuclyybpmnqglhlutlujucjmndtaksa-4", "gzunekavgfjatwafayqhzcjpulgfmbulnnnm-16", "pakbnqtpnrbuwizuhgznbxpgdwzfhqoonvfh-4", "hfuxzlhqzyeisilfflfwqopvsityozsqcwum-4"]
		},
		{
			"uid": "group17",
			"label": "leuO_1",
			"genes": []
		},
		{
			"uid": "group18",
			"label": "leuA",
			"genes": ["syzazxvdjgbnnqrsoxdlbmvhdlvwjbwhohpb-18", "shncgijylmrzyxngguztabvawkcocibthsit-2", "kokqyqyrupwkmphgvafeziybldkujwrmqstx-2", "fibnrjmrupgbvqncwcspjxlfdqdbqwvuesum-2", "tmbumlpqopzbkiqwcnzbysiajbveyatjqchf-18", "lkmhkflfaiuhikosucymdifroqxdkhoupifr-2", "srhwliukqgwasifxrnnjmlxxipiqietrykhi-18", "lzezkmktpaooltqqxjjshhwuwzvqgatfnyhk-18", "kmrjuxgfqadpgxwzajvjfhpjefrfhsrkdjps-18", "bsbygludomgyeflqopmnlhuillvbywooarwx-2", "jknobwuclyybpmnqglhlutlujucjmndtaksa-2", "gzunekavgfjatwafayqhzcjpulgfmbulnnnm-18", "pakbnqtpnrbuwizuhgznbxpgdwzfhqoonvfh-2", "hfuxzlhqzyeisilfflfwqopvsityozsqcwum-2"]
		},
		{
			"uid": "group19",
			"label": "leuB",
			"genes": ["syzazxvdjgbnnqrsoxdlbmvhdlvwjbwhohpb-19", "shncgijylmrzyxngguztabvawkcocibthsit-1", "kokqyqyrupwkmphgvafeziybldkujwrmqstx-1", "fibnrjmrupgbvqncwcspjxlfdqdbqwvuesum-1", "tmbumlpqopzbkiqwcnzbysiajbveyatjqchf-19", "lkmhkflfaiuhikosucymdifroqxdkhoupifr-1", "srhwliukqgwasifxrnnjmlxxipiqietrykhi-19", "lzezkmktpaooltqqxjjshhwuwzvqgatfnyhk-19", "kmrjuxgfqadpgxwzajvjfhpjefrfhsrkdjps-19", "bsbygludomgyeflqopmnlhuillvbywooarwx-1", "jknobwuclyybpmnqglhlutlujucjmndtaksa-1", "gzunekavgfjatwafayqhzcjpulgfmbulnnnm-19", "pakbnqtpnrbuwizuhgznbxpgdwzfhqoonvfh-1", "hfuxzlhqzyeisilfflfwqopvsityozsqcwum-1"]
		},
		{
			"uid": "group20",
			"label": "leuC1",
			"genes": ["syzazxvdjgbnnqrsoxdlbmvhdlvwjbwhohpb-20", "shncgijylmrzyxngguztabvawkcocibthsit-0", "kokqyqyrupwkmphgvafeziybldkujwrmqstx-0", "fibnrjmrupgbvqncwcspjxlfdqdbqwvuesum-0", "tmbumlpqopzbkiqwcnzbysiajbveyatjqchf-20", "lkmhkflfaiuhikosucymdifroqxdkhoupifr-0", "srhwliukqgwasifxrnnjmlxxipiqietrykhi-20", "lzezkmktpaooltqqxjjshhwuwzvqgatfnyhk-20", "kmrjuxgfqadpgxwzajvjfhpjefrfhsrkdjps-20", "bsbygludomgyeflqopmnlhuillvbywooarwx-0", "jknobwuclyybpmnqglhlutlujucjmndtaksa-0", "gzunekavgfjatwafayqhzcjpulgfmbulnnnm-20", "pakbnqtpnrbuwizuhgznbxpgdwzfhqoonvfh-0", "hfuxzlhqzyeisilfflfwqopvsityozsqcwum-0"]
		},
		{
			"uid": "group21",
			"label": "leuO",
			"genes": ["syzazxvdjgbnnqrsoxdlbmvhdlvwjbwhohpb-17", "shncgijylmrzyxngguztabvawkcocibthsit-3", "kokqyqyrupwkmphgvafeziybldkujwrmqstx-3", "fibnrjmrupgbvqncwcspjxlfdqdbqwvuesum-3", "tmbumlpqopzbkiqwcnzbysiajbveyatjqchf-17", "lkmhkflfaiuhikosucymdifroqxdkhoupifr-3", "srhwliukqgwasifxrnnjmlxxipiqietrykhi-17", "lzezkmktpaooltqqxjjshhwuwzvqgatfnyhk-17", "kmrjuxgfqadpgxwzajvjfhpjefrfhsrkdjps-17", "bsbygludomgyeflqopmnlhuillvbywooarwx-3", "jknobwuclyybpmnqglhlutlujucjmndtaksa-3", "gzunekavgfjatwafayqhzcjpulgfmbulnnnm-17", "pakbnqtpnrbuwizuhgznbxpgdwzfhqoonvfh-3", "hfuxzlhqzyeisilfflfwqopvsityozsqcwum-3"]
		},
		{
			"uid": "group22",
			"label": "ftsA_1",
			"genes": ["shncgijylmrzyxngguztabvawkcocibthsit-20", "kokqyqyrupwkmphgvafeziybldkujwrmqstx-20", "tmbumlpqopzbkiqwcnzbysiajbveyatjqchf-0", "lkmhkflfaiuhikosucymdifroqxdkhoupifr-20", "kmrjuxgfqadpgxwzajvjfhpjefrfhsrkdjps-0", "bsbygludomgyeflqopmnlhuillvbywooarwx-20", "jknobwuclyybpmnqglhlutlujucjmndtaksa-20", "pakbnqtpnrbuwizuhgznbxpgdwzfhqoonvfh-20"]
		},
		{
			"uid": "group23",
			"label": "ftsI_1",
			"genes": ["tmbumlpqopzbkiqwcnzbysiajbveyatjqchf-10", "srhwliukqgwasifxrnnjmlxxipiqietrykhi-10", "gzunekavgfjatwafayqhzcjpulgfmbulnnnm-10"]
		}
	]
}
